esetconnect/__init__.py
esetconnect/client.py
esetconnect/const.py
esetconnect/models/__init__.py
esetconnect/models/authorization.py
esetconnect/models/detections.py
esetconnect/models/devices.py
esetconnect/models/epc.py
esetconnect/py.typed
esetconnect/urls/__init__.py
esetconnect/urls/authorization.py
esetconnect/urls/base.py
esetconnect/urls/detections.py
esetconnect-0.1.1.dist-info/WHEEL
esetconnect-0.1.1.dist-info/METADATA
esetconnect-0.1.1.dist-info/RECORD
